lastweet.py
setup.py
lastweet.egg-info/PKG-INFO
lastweet.egg-info/SOURCES.txt
lastweet.egg-info/dependency_links.txt
lastweet.egg-info/requires.txt
lastweet.egg-info/top_level.txt