Metadata-Version: 1.0
Name: lastweet
Version: 0.0.3
Summary: Send Twitter/Mastodon updates about LastFM activity
Home-page: http://github.com/edsu/lastweet
Author: Ed Summers
Author-email: ehs@pobox.com
License: UNKNOWN
Platform: UNKNOWN
